CHANGES.rst
MANIFEST.in
README.rst
setup.cfg
setup.py
docs/Makefile
docs/make.bat
docs/readthedocs-requirements.txt
docs/_images/controlpanel_base.png
docs/_images/controlpanel_caching.png
docs/_images/controlpanel_contact_info_agency.png
docs/_images/controlpanel_contact_info_agent.png
docs/_images/controlpanel_contact_info_default.png
docs/_images/controlpanel_ui.png
docs/_images/controlpanel_usage.png
docs/_images/development_collection_activate.png
docs/_images/development_collection_activate_done.png
docs/_images/development_collection_configuration.png
docs/_images/development_collection_configuration_filter.png
docs/_images/development_collection_deactivate.png
docs/_images/development_collection_deactivate_done.png
docs/_images/development_collection_default.png
docs/_images/development_collection_with_banner.png
docs/_images/listing_collection_activate.png
docs/_images/listing_collection_activate_done.png
docs/_images/listing_collection_configuration.png
docs/_images/listing_collection_deactivate.png
docs/_images/listing_collection_deactivate_done.png
docs/_images/listing_collection_default.png
docs/_images/listing_search_activate.png
docs/_images/listing_search_activate_done.png
docs/_images/listing_search_configuration.png
docs/_images/listing_search_deactivate.png
docs/_images/listing_search_deactivate_done.png
docs/_images/listing_search_default.png
docs/_images/recent_listings_activate.png
docs/_images/recent_listings_activate_done.png
docs/_images/recent_listings_configuration.png
docs/_images/recent_listings_deactivate.png
docs/_images/recent_listings_deactivate_done.png
docs/_images/recent_listings_default.png
docs/_images/setup_select_add_on.png
docs/_images/setup_select_add_on_installable.png
docs/source/conf.py
docs/source/configuration.rst
docs/source/index.rst
docs/source/install.rst
docs/source/_static/empty
docs/source/_static/logo.png
docs/source/_templates/empty
docs/source/developments/collection.rst
docs/source/developments/details.rst
src/ps.plone.mls.egg-info/PKG-INFO
src/ps.plone.mls.egg-info/SOURCES.txt
src/ps.plone.mls.egg-info/dependency_links.txt
src/ps.plone.mls.egg-info/entry_points.txt
src/ps.plone.mls.egg-info/namespace_packages.txt
src/ps.plone.mls.egg-info/not-zip-safe
src/ps.plone.mls.egg-info/requires.txt
src/ps.plone.mls.egg-info/top_level.txt
